sttk/__init__.py
sttk/charting/__init__.py
sttk/charting/indicators.py
sttk/charting/main.py
sttk/charting/plot.py
sttk/data/__init__.py
sttk/data/yfdownload.py
sttk/researchtools/__init__.py
sttk/researchtools/csvinspector.py
sttk-0.2.1.dist-info/LICENSE
sttk-0.2.1.dist-info/METADATA
sttk-0.2.1.dist-info/WHEEL
sttk-0.2.1.dist-info/RECORD
